README.txt
setup.cfg
setup.py
tg_interface/__init__.py
tg_interface/release.py
tg_interface/widgets.py
tg_interface.egg-info/PKG-INFO
tg_interface.egg-info/SOURCES.txt
tg_interface.egg-info/dependency_links.txt
tg_interface.egg-info/entry_points.txt
tg_interface.egg-info/not-zip-safe
tg_interface.egg-info/paster_plugins.txt
tg_interface.egg-info/requires.txt
tg_interface.egg-info/sqlobject.txt
tg_interface.egg-info/top_level.txt
