Metadata-Version: 1.0
Name: tg-interface
Version: 1.2-0.01
Summary: interface.js javascript library for TurboGears
Home-page: UNKNOWN
Author: Derek Anderson
Author-email: derek@enomaly.com
License: MIT
Keywords: turbogears.widgets
Platform: UNKNOWN
Classifier: Development Status :: 3 - Alpha
Classifier: Operating System :: OS Independent
Classifier: Programming Language :: Python
Classifier: Topic :: Software Development :: Libraries :: Python Modules
Classifier: Framework :: TurboGears
Classifier: Framework :: TurboGears :: Widgets
